PyQt4Enhanced/main.py
PyQt4Enhanced/__init__.py
PyQt4Enhanced-0.1.1.dist-info/top_level.txt
PyQt4Enhanced-0.1.1.dist-info/metadata.json
PyQt4Enhanced-0.1.1.dist-info/WHEEL
PyQt4Enhanced-0.1.1.dist-info/RECORD
PyQt4Enhanced-0.1.1.dist-info/METADATA
PyQt4Enhanced-0.1.1.dist-info/DESCRIPTION.rst
