Metadata-Version: 1.0
Name: PyQt4Enhanced
Version: 0.1.1
Summary: Enhanced PyQt4 module
Home-page: https://github.com/finn-christiansen/PyQt4Enhanced
Author: Finn Christiansen
Author-email: mail@finnchristiansen.com
License: to set
Platform: UNKNOWN
